{"nodes": [{"id": "scripts_run_goal_py", "label": "run_goal.py", "file_type": "code", "source_file": "scripts/run_goal.py", "source_location": "L1"}, {"id": "run_goal_main", "label": "main()", "file_type": "code", "source_file": "scripts/run_goal.py", "source_location": "L8"}], "edges": [{"source": "scripts_run_goal_py", "target": "argparse", "relation": "imports", "confidence": "EXTRACTED", "source_file": "scripts/run_goal.py", "source_location": "L3", "weight": 1.0}, {"source": "scripts_run_goal_py", "target": "serving_runtime", "relation": "imports_from", "confidence": "EXTRACTED", "source_file": "scripts/run_goal.py", "source_location": "L5", "weight": 1.0}, {"source": "scripts_run_goal_py", "target": "run_goal_main", "relation": "contains", "confidence": "EXTRACTED", "source_file": "scripts/run_goal.py", "source_location": "L8", "weight": 1.0}], "raw_calls": [{"caller_nid": "run_goal_main", "callee": "ArgumentParser", "source_file": "scripts/run_goal.py", "source_location": "L9"}, {"caller_nid": "run_goal_main", "callee": "add_argument", "source_file": "scripts/run_goal.py", "source_location": "L10"}, {"caller_nid": "run_goal_main", "callee": "add_argument", "source_file": "scripts/run_goal.py", "source_location": "L11"}, {"caller_nid": "run_goal_main", "callee": "parse_args", "source_file": "scripts/run_goal.py", "source_location": "L12"}, {"caller_nid": "run_goal_main", "callee": "AgentRuntime", "source_file": "scripts/run_goal.py", "source_location": "L14"}, {"caller_nid": "run_goal_main", "callee": "step", "source_file": "scripts/run_goal.py", "source_location": "L15"}, {"caller_nid": "run_goal_main", "callee": "join", "source_file": "scripts/run_goal.py", "source_location": "L15"}, {"caller_nid": "run_goal_main", "callee": "write_jsonl", "source_file": "scripts/run_goal.py", "source_location": "L16"}, {"caller_nid": "run_goal_main", "callee": "print", "source_file": "scripts/run_goal.py", "source_location": "L18"}]}