{"nodes": [{"id": "scripts_verify_all_py", "label": "verify_all.py", "file_type": "code", "source_file": "scripts/verify_all.py", "source_location": "L1"}, {"id": "verify_all_main", "label": "main()", "file_type": "code", "source_file": "scripts/verify_all.py", "source_location": "L10"}], "edges": [{"source": "scripts_verify_all_py", "target": "verifiers_code", "relation": "imports_from", "confidence": "EXTRACTED", "source_file": "scripts/verify_all.py", "source_location": "L3", "weight": 1.0}, {"source": "scripts_verify_all_py", "target": "training_loops_train_neural_jepa", "relation": "imports_from", "confidence": "EXTRACTED", "source_file": "scripts/verify_all.py", "source_location": "L4", "weight": 1.0}, {"source": "scripts_verify_all_py", "target": "training_loops_train_torch_jepa", "relation": "imports_from", "confidence": "EXTRACTED", "source_file": "scripts/verify_all.py", "source_location": "L5", "weight": 1.0}, {"source": "scripts_verify_all_py", "target": "torch_backend_config", "relation": "imports_from", "confidence": "EXTRACTED", "source_file": "scripts/verify_all.py", "source_location": "L6", "weight": 1.0}, {"source": "scripts_verify_all_py", "target": "tools_shell", "relation": "imports_from", "confidence": "EXTRACTED", "source_file": "scripts/verify_all.py", "source_location": "L7", "weight": 1.0}, {"source": "scripts_verify_all_py", "target": "verify_all_main", "relation": "contains", "confidence": "EXTRACTED", "source_file": "scripts/verify_all.py", "source_location": "L10", "weight": 1.0}], "raw_calls": [{"caller_nid": "verify_all_main", "callee": "CodeVerifier", "source_file": "scripts/verify_all.py", "source_location": "L11"}, {"caller_nid": "verify_all_main", "callee": "ShellTool", "source_file": "scripts/verify_all.py", "source_location": "L12"}, {"caller_nid": "verify_all_main", "callee": "compile_python", "source_file": "scripts/verify_all.py", "source_location": "L13"}, {"caller_nid": "verify_all_main", "callee": "pytest", "source_file": "scripts/verify_all.py", "source_location": "L14"}, {"caller_nid": "verify_all_main", "callee": "train_neural_jepa", "source_file": "scripts/verify_all.py", "source_location": "L15"}, {"caller_nid": "verify_all_main", "callee": "train_jepa_torch", "source_file": "scripts/verify_all.py", "source_location": "L16"}, {"caller_nid": "verify_all_main", "callee": "TorchTrainConfig", "source_file": "scripts/verify_all.py", "source_location": "L17"}, {"caller_nid": "verify_all_main", "callee": "TorchModelConfig", "source_file": "scripts/verify_all.py", "source_location": "L23"}, {"caller_nid": "verify_all_main", "callee": "run", "source_file": "scripts/verify_all.py", "source_location": "L25"}, {"caller_nid": "verify_all_main", "callee": "run", "source_file": "scripts/verify_all.py", "source_location": "L26"}, {"caller_nid": "verify_all_main", "callee": "print", "source_file": "scripts/verify_all.py", "source_location": "L27"}, {"caller_nid": "verify_all_main", "callee": "SystemExit", "source_file": "scripts/verify_all.py", "source_location": "L47"}]}